README.md
setup.py
gdpr_check/__init__.py
gdpr_check/checker.py
gdpr_check.egg-info/PKG-INFO
gdpr_check.egg-info/SOURCES.txt
gdpr_check.egg-info/dependency_links.txt
gdpr_check.egg-info/requires.txt
gdpr_check.egg-info/top_level.txt