Metadata-Version: 2.1
Name: gdpr-check
Version: 0.8
Summary: Check if a user is covered by GDPR. Compare IP address to list of EEA/EU countries.
Home-page: http://github.com/revmischa/gdpr_check
Author: Mischa Spiegelmock
Author-email: revmischa@cpan.org
License: ABRMS
Keywords: gdpr eea eu ip check geoip country
Platform: UNKNOWN
